[
  {
    "tag_name": "entity",
    "ids_to_tags": {
      "1": "B-Q_answer",
      "2": "I-Q_answer",
      "3": "L-Q_answer",
      "4": "U-Q_answer",
      "5": "B-get_number",
      "6": "I-get_number",
      "7": "L-get_number",
      "8": "U-get_number",
      "9": "B-question_num",
      "10": "I-question_num",
      "11": "L-question_num",
      "12": "U-question_num",
      "0": "O"
    },
    "tags_to_ids": {
      "B-Q_answer": 1,
      "I-Q_answer": 2,
      "L-Q_answer": 3,
      "U-Q_answer": 4,
      "B-get_number": 5,
      "I-get_number": 6,
      "L-get_number": 7,
      "U-get_number": 8,
      "B-question_num": 9,
      "I-question_num": 10,
      "L-question_num": 11,
      "U-question_num": 12,
      "O": 0
    },
    "num_tags": 13
  }
]